pyarrot/__init__.py
pyarrot/pyarrot.py
pyarrot-0.1.2.dist-info/LICENSE
pyarrot-0.1.2.dist-info/METADATA
pyarrot-0.1.2.dist-info/WHEEL
pyarrot-0.1.2.dist-info/top_level.txt
pyarrot-0.1.2.dist-info/RECORD
