Metadata-Version: 2.1
Name: pyarrot
Version: 0.1.2
Summary: Helper functions for interactive mode.
Home-page: https://github.com/yuukimiyo/PyArrot
Author: yuuki miyoshi
Author-email: yuuki.miyo@gmail.com
License: MIT
Keywords: interactive batch
Platform: UNKNOWN
Classifier: Programming Language :: Python :: 2
Classifier: Programming Language :: Python :: 3
Classifier: License :: OSI Approved :: MIT License
